matchgreek/__init__.py
matchgreek/matchgreek.py
matchgreek-0.1.1.dist-info/DESCRIPTION.rst
matchgreek-0.1.1.dist-info/METADATA
matchgreek-0.1.1.dist-info/RECORD
matchgreek-0.1.1.dist-info/WHEEL
matchgreek-0.1.1.dist-info/entry_points.txt
matchgreek-0.1.1.dist-info/metadata.json
matchgreek-0.1.1.dist-info/top_level.txt
